{
  "STABLE": {
    "entry_time": "2025-12-27T17:43:28.573236",
    "entry_price": 0.013538,
    "entry_volume": 2353952.753538999,
    "current_price": 0.014487,
    "current_volume": 2215479.636918,
    "max_price": 0.015006,
    "min_price": 0.013538,
    "in_top6": true
  },
  "DOT": {
    "entry_time": "2025-12-27T18:50:22.349602",
    "entry_price": 1.8396,
    "entry_volume": 1596876.8088000007,
    "current_price": 1.8272,
    "current_volume": 1607571.78614,
    "max_price": 1.8396,
    "min_price": 1.8272,
    "in_top6": true
  },
  "FOGO": {
    "entry_time": "2025-12-27T18:59:01.547993",
    "entry_price": 0.215,
    "entry_volume": 1176497.0671599999,
    "current_price": 0.22449,
    "current_volume": 1158173.4577199998,
    "max_price": 0.22449,
    "min_price": 0.215,
    "in_top6": true
  },
  "MNT": {
    "entry_time": "2025-12-27T19:26:21.224894",
    "entry_price": 1.0524,
    "entry_volume": 475974.12428,
    "current_price": 1.0517,
    "current_volume": 476961.2578399999,
    "max_price": 1.0526,
    "min_price": 1.0517,
    "in_top6": true
  },
  "CC": {
    "entry_time": "2025-12-27T19:39:55.735687",
    "entry_price": 0.11272,
    "entry_volume": 1680182.6113969993,
    "current_price": 0.11272,
    "current_volume": 1680182.6113969993,
    "max_price": 0.11272,
    "min_price": 0.11272,
    "in_top6": true
  },
  "AVNT": {
    "entry_time": "2025-12-27T19:39:55.735687",
    "entry_price": 0.40389,
    "entry_volume": 5642283.4351200005,
    "current_price": 0.40389,
    "current_volume": 5642283.4351200005,
    "max_price": 0.40389,
    "min_price": 0.40389,
    "in_top6": true
  }
}